README.md
setup.py
electron_api/__init__.py
electron_api/api_client.py
electron_api/auth_api.py
electron_api/configuration.py
electron_api/environment.py
electron_api/rest.py
electron_api/api/__init__.py
electron_api/api/ach_api.py
electron_api/api/card_api.py
electron_api/models/__init__.py
electron_api/models/ach_card_request_co.py
electron_api/models/ach_card_response_vo.py
electron_api/models/base_response_vo.py
electron_api/models/card_base_request_co.py
electron_api/models/card_client_request_co.py
electron_api/models/card_load_request_co.py
electron_api/models/card_load_unload_response_vo.py
electron_api/models/card_replace_response_vo.py
electron_api/models/card_reserve_account_response_vo.py
electron_api/models/card_spending_control_request_co.py
electron_api/models/card_spending_control_response_vo.py
electron_api/models/card_unload_request_co.py
electron_api/models/create_card_client_response_vo.py
electron_api/models/spending_control_vendor_request_data_vo.py
electron_api/models/update_card_client_response_vo.py
hydrogen_electron_api.egg-info/PKG-INFO
hydrogen_electron_api.egg-info/SOURCES.txt
hydrogen_electron_api.egg-info/dependency_links.txt
hydrogen_electron_api.egg-info/requires.txt
hydrogen_electron_api.egg-info/top_level.txt
test/__init__.py
test/test_ach_api.py
test/test_ach_card_request_co.py
test/test_ach_card_response_vo.py
test/test_base_response_vo.py
test/test_card_api.py
test/test_card_base_request_co.py
test/test_card_client_request_co.py
test/test_card_load_request_co.py
test/test_card_load_unload_response_vo.py
test/test_card_replace_response_vo.py
test/test_card_reserve_account_response_vo.py
test/test_card_spending_control_request_co.py
test/test_card_spending_control_response_vo.py
test/test_card_unload_request_co.py
test/test_create_card_client_response_vo.py
test/test_spending_control_vendor_request_data_vo.py
test/test_update_card_client_response_vo.py