Metadata-Version: 1.0
Name: hydrogen-electron-api
Version: 1.3.1
Summary: Hydrogen Electron API
Home-page: https://www.hydrogenplatform.com
Author: UNKNOWN
Author-email: info@hydrogenplatform.com
License: UNKNOWN
Keywords: Swagger,Hydrogen Electron API
Platform: UNKNOWN
